auto_backup_storage/__init__.py
auto_backup_storage/auto_backup_storage.py
auto_backup_storage/cli.py
auto_backup_storage/package_version.txt
auto_backup_storage-1.1.1.dist-info/LICENSE
auto_backup_storage-1.1.1.dist-info/METADATA
auto_backup_storage-1.1.1.dist-info/WHEEL
auto_backup_storage-1.1.1.dist-info/entry_points.txt
auto_backup_storage-1.1.1.dist-info/top_level.txt
auto_backup_storage-1.1.1.dist-info/RECORD
