Metadata-Version: 2.1
Name: auto_backup_storage
Version: 1.1.1
Summary: A Python script for backing up and synchronizing data between SSD and HDD with CPU usage monitoring.
Home-page: https://github.com/datlt4/auto_backup_storage
Author: Koi
Author-email: your.email@example.com
Classifier: Programming Language :: Python :: 3
Classifier: License :: OSI Approved :: MIT License
Classifier: Operating System :: OS Independent
Requires-Python: >=3.6
License-File: LICENSE
Requires-Dist: psutil
